licensechain/__init__.py
licensechain/api_client.py
licensechain/client.py
licensechain/enhanced_client.py
licensechain/exceptions.py
licensechain/license_validator.py
licensechain/models.py
licensechain/simple_client.py
licensechain/utils.py
licensechain/webhook_handler.py
licensechain/webhook_verifier.py
licensechain/services/__init__.py
licensechain/services/license_service.py
licensechain/services/product_service.py
licensechain/services/user_service.py
licensechain/services/webhook_service.py
licensechain_sdk-1.1.3.dist-info/licenses/LICENSE
licensechain_sdk-1.1.3.dist-info/METADATA
licensechain_sdk-1.1.3.dist-info/WHEEL
licensechain_sdk-1.1.3.dist-info/top_level.txt
licensechain_sdk-1.1.3.dist-info/RECORD
